AUTHORS
LICENSE
MANIFEST.in
setup.cfg
setup.py
MUS/CommandLineInterface.py
MUS/MSBWTGen.py
MUS/MultiStringBWT.py
MUS/TranscriptBuilder.py
MUS/__init__.py
MUS/util.py
MUSCython/AlignmentUtil.c
MUSCython/AlignmentUtil.pyx
MUSCython/BasicBWT.c
MUSCython/BasicBWT.pxd
MUSCython/BasicBWT.pyx
MUSCython/ByteBWTCython.c
MUSCython/ByteBWTCython.pyx
MUSCython/CompressToRLE.c
MUSCython/CompressToRLE.pyx
MUSCython/GenericMerge.c
MUSCython/GenericMerge.pyx
MUSCython/LCPGen.c
MUSCython/LCPGen.pyx
MUSCython/LZW_BWTCython.c
MUSCython/LZW_BWTCython.pyx
MUSCython/MSBWTCompGenCython.c
MUSCython/MSBWTCompGenCython.pyx
MUSCython/MSBWTGenCython.c
MUSCython/MSBWTGenCython.pyx
MUSCython/MultiStringBWTCython.c
MUSCython/MultiStringBWTCython.pyx
MUSCython/MultimergeCython.c
MUSCython/MultimergeCython.pyx
MUSCython/RLE_BWTCython.c
MUSCython/RLE_BWTCython.pyx
MUSCython/TranscriptCorrector.pyx
MUSCython/TranscriptCorrector2.pyx
MUSCython/__init__.py
bin/msbwt
msbwt.egg-info/PKG-INFO
msbwt.egg-info/SOURCES.txt
msbwt.egg-info/dependency_links.txt
msbwt.egg-info/not-zip-safe
msbwt.egg-info/requires.txt
msbwt.egg-info/top_level.txt