Metadata-Version: 1.0
Name: msbwt
Version: 0.3.0
Summary: Allows for merging and querying of multi-string BWTs for genomic strings
Home-page: http://code.google.com/p/msbwt
Author: James Holt
Author-email: holtjma@cs.unc.edu
License: MIT
Platform: UNKNOWN
